.gitignore
CHANGELOG.md
LICENSE
MANIFEST.in
README.rst
mkdeb.sh
requirements.txt
setup.py
.github/workflows/python-3.10.yml
hszinc/__init__.py
hszinc/datatypes.py
hszinc/dumper.py
hszinc/filter_ast.py
hszinc/grid.py
hszinc/grid_filter.py
hszinc/jsondumper.py
hszinc/jsonparser.py
hszinc/metadata.py
hszinc/parser.py
hszinc/pintutil.py
hszinc/sortabledict.py
hszinc/version.py
hszinc/zincdumper.py
hszinc/zincparser.py
hszinc/zoneinfo.py
hszinc.egg-info/PKG-INFO
hszinc.egg-info/SOURCES.txt
hszinc.egg-info/dependency_links.txt
hszinc.egg-info/requires.txt
hszinc.egg-info/top_level.txt
tests/__init__.py
tests/pint_enable.py
tests/pint_units.py
tests/project_haystack_units.txt
tests/sortabledict_tests.py
tests/test_acid.py
tests/test_datatype.py
tests/test_dumper.py
tests/test_filter.py
tests/test_grid.py
tests/test_import.py
tests/test_parser.py
tests/test_pint.py
tests/test_version.py
tests/test_zoneinfo.py
tests/units.pckl
tests/data/wc1382-unicode-grid.txt