Metadata-Version: 2.1
Name: hszinc
Version: 1.3.2
Summary: Parser and dumper for Project Haystack ZINC (Zinc is not CSV) file format
Home-page: https://github.com/vrtsystems/hszinc
Author: VRT Systems
Author-email: support@vrt.com.au
License: BSD
Classifier: Development Status :: 4 - Beta
Classifier: Environment :: No Input/Output (Daemon)
Classifier: Environment :: Other Environment
Classifier: Intended Audience :: Developers
Classifier: License :: OSI Approved :: BSD License
Classifier: Programming Language :: Python
Classifier: Programming Language :: Python :: 2.7
Classifier: Programming Language :: Python :: 3.4
Classifier: Programming Language :: Python :: 3.5
Classifier: Programming Language :: Python :: 3.6
Classifier: Programming Language :: Python :: 3.7
Classifier: Topic :: Scientific/Engineering
Classifier: Topic :: Scientific/Engineering :: Information Analysis
Classifier: Topic :: Software Development :: Libraries :: Python Modules
Requires: pyparsing
Requires: pytz
Requires: iso8601
Requires: six
Provides-Extra: unitconversion
License-File: LICENSE
